xlsxreader/__init__.py
xlsxreader/xlsxreader.py
test_xlsxreader_test-0.0.2.dist-info/LICENSE
test_xlsxreader_test-0.0.2.dist-info/METADATA
test_xlsxreader_test-0.0.2.dist-info/WHEEL
test_xlsxreader_test-0.0.2.dist-info/top_level.txt
test_xlsxreader_test-0.0.2.dist-info/RECORD
