Metadata-Version: 2.1
Name: test-xlsxreader-test
Version: 0.0.2
Summary: test xlsxreader
Home-page: https://github.com/michael-brine/xlsxreader
Author: Michael Brine
Author-email: mbrine0@gmail.com
License: UNKNOWN
Project-URL: Bug Tracker, https://github.com/michael-brine/xlsxreader
Platform: UNKNOWN
Classifier: Programming Language :: Python :: 3
Classifier: License :: OSI Approved :: MIT License
Classifier: Operating System :: OS Independent
Requires-Python: >=3.6
License-File: LICENSE
